README.md
setup.cfg
setup.py
TOPSIS/__init__.py
TOPSIS/__main__.py
TOPSIS_Aashima_101803213.egg-info/PKG-INFO
TOPSIS_Aashima_101803213.egg-info/SOURCES.txt
TOPSIS_Aashima_101803213.egg-info/dependency_links.txt
TOPSIS_Aashima_101803213.egg-info/entry_points.txt
TOPSIS_Aashima_101803213.egg-info/top_level.txt